dxcampil/__init__.py
dxcampil/dxcam.py
dxcampil/_libs/__init__.py
dxcampil/_libs/d3d11.py
dxcampil/_libs/dxgi.py
dxcampil/_libs/user32.py
dxcampil/core/__init__.py
dxcampil/core/device.py
dxcampil/core/duplicator.py
dxcampil/core/output.py
dxcampil/core/stagesurf.py
dxcampil/processor/__init__.py
dxcampil/processor/base.py
dxcampil/processor/pillow_processor.py
dxcampil/util/__init__.py
dxcampil/util/io.py
dxcampil/util/timer.py
dxcampil-0.0.5.dist-info/LICENSE
dxcampil-0.0.5.dist-info/METADATA
dxcampil-0.0.5.dist-info/WHEEL
dxcampil-0.0.5.dist-info/top_level.txt
dxcampil-0.0.5.dist-info/RECORD
