Metadata-Version: 2.1
Name: dxcampil
Version: 0.0.5
Summary: A Python high-performance screenshot library for Windows use Desktop Duplication API
Home-page: https://github.com/hite4044/DXcamPIL
Author: hite4044
License: MIT
Project-URL: Source, https://github.com/hite4044/DXcamPIL
Project-URL: Tracker, https://github.com/hite4044/DXcamPIL/issues
Keywords: screen,screenshot,screencapture,screengrab,windows
Classifier: Development Status :: 2 - Pre-Alpha
Classifier: Intended Audience :: Developers
Classifier: Programming Language :: Python :: 3
Classifier: Programming Language :: Python :: 3 :: Only
Classifier: License :: OSI Approved :: MIT License
Classifier: Operating System :: Microsoft :: Windows
Classifier: Operating System :: Microsoft :: Windows :: Windows 8.1
Classifier: Operating System :: Microsoft :: Windows :: Windows 10
Classifier: Topic :: Multimedia :: Graphics
Classifier: Topic :: Multimedia :: Graphics :: Capture
Classifier: Topic :: Multimedia :: Graphics :: Capture :: Screen Capture
Requires-Python: >=3.7
License-File: LICENSE
Requires-Dist: comtypes
Requires-Dist: pillow
